CHANGES.txt
COPYRIGHT.txt
MANIFEST.in
README.txt
ZopePublicLicense.txt
bootstrap.py
buildout.cfg
setup.py
src/zope/__init__.py
src/zope.html.egg-info/PKG-INFO
src/zope.html.egg-info/SOURCES.txt
src/zope.html.egg-info/dependency_links.txt
src/zope.html.egg-info/namespace_packages.txt
src/zope.html.egg-info/not-zip-safe
src/zope.html.egg-info/requires.txt
src/zope.html.egg-info/top_level.txt
src/zope/html/README.txt
src/zope/html/TODO.txt
src/zope/html/__init__.py
src/zope/html/browser.py
src/zope/html/browser.txt
src/zope/html/configure.zcml
src/zope/html/docinfo.py
src/zope/html/docinfo.txt
src/zope/html/field.py
src/zope/html/ftesting.zcml
src/zope/html/i18n.py
src/zope/html/interfaces.py
src/zope/html/tests.py
src/zope/html/widget.py
src/zope/html/widget.txt
src/zope/html/zope_ckconfig.js
src/zope/html/zope_fckconfig.js
src/zope/html/ckeditor/.htaccess
src/zope/html/ckeditor/3.6.2/ckeditor/.htaccess
src/zope/html/ckeditor/3.6.2/ckeditor/CHANGES.html
src/zope/html/ckeditor/3.6.2/ckeditor/INSTALL.html
src/zope/html/ckeditor/3.6.2/ckeditor/LICENSE.html
src/zope/html/ckeditor/3.6.2/ckeditor/ckeditor.asp
src/zope/html/ckeditor/3.6.2/ckeditor/ckeditor.js
src/zope/html/ckeditor/3.6.2/ckeditor/ckeditor.pack
src/zope/html/ckeditor/3.6.2/ckeditor/ckeditor.php
src/zope/html/ckeditor/3.6.2/ckeditor/ckeditor_basic.js
src/zope/html/ckeditor/3.6.2/ckeditor/ckeditor_basic_source.js
src/zope/html/ckeditor/3.6.2/ckeditor/ckeditor_php4.php
src/zope/html/ckeditor/3.6.2/ckeditor/ckeditor_php5.php
src/zope/html/ckeditor/3.6.2/ckeditor/ckeditor_source.js
src/zope/html/ckeditor/3.6.2/ckeditor/config.js
src/zope/html/ckeditor/3.6.2/ckeditor/contents.css
src/zope/html/ckeditor/3.6.2/ckeditor/_samples/ajax.html
src/zope/html/ckeditor/3.6.2/ckeditor/_samples/api.html
src/zope/html/ckeditor/3.6.2/ckeditor/_samples/api_dialog.html
src/zope/html/ckeditor/3.6.2/ckeditor/_samples/autogrow.html
src/zope/html/ckeditor/3.6.2/ckeditor/_samples/bbcode.html
src/zope/html/ckeditor/3.6.2/ckeditor/_samples/devtools.html
src/zope/html/ckeditor/3.6.2/ckeditor/_samples/divreplace.html
src/zope/html/ckeditor/3.6.2/ckeditor/_samples/enterkey.html
src/zope/html/ckeditor/3.6.2/ckeditor/_samples/fullpage.html
src/zope/html/ckeditor/3.6.2/ckeditor/_samples/index.html
